connorama/Back.py
connorama/Style.py
connorama/Text.py
connorama/__init__.py
connorama-0.0.3.dist-info/LICENSE
connorama-0.0.3.dist-info/METADATA
connorama-0.0.3.dist-info/WHEEL
connorama-0.0.3.dist-info/top_level.txt
connorama-0.0.3.dist-info/RECORD
