Metadata-Version: 2.1
Name: connorama
Version: 0.0.3
Summary: colours for python terminal
Home-page: https://github.com/connorstott/connorama
Author: Connor Stott
Author-email: connorbstott@gmail.com
License: UNKNOWN
Platform: UNKNOWN
Classifier: Programming Language :: Python :: 3
Classifier: License :: OSI Approved :: MIT License
Classifier: Operating System :: OS Independent
Requires-Python: >3.0
License-File: LICENSE
